{
  "format": ["stdmap", 1],
  "locations": {
    "area_of_interest_bounds": [
      {"center": [0.0, 7.14, -0.02], "size": [21.13, 4.96, 16.69]}
    ],
    "ffa_spawn": [
      {"center": [-4.21, 6.97, -3.79], "size": [0.39, 1.16, 0.3]},
      {"center": [7.38, 5.21, -2.79], "size": [1.16, 1.16, 1.16]},
      {"center": [-7.26, 5.46, -3.1], "size": [1.16, 1.16, 1.16]},
      {"center": [0.02, 5.37, 4.08], "size": [1.88, 1.16, 0.2]},
      {"center": [-1.57, 7.04, -0.48], "size": [0.39, 1.16, 0.3]},
      {"center": [1.69, 7.04, -0.48], "size": [0.39, 1.16, 0.3]},
      {"center": [4.4, 6.97, -3.8], "size": [0.39, 1.16, 0.3]}
    ],
    "flag": [
      {"center": [-7.01, 5.42, -2.72]},
      {"center": [7.17, 5.17, -2.65]}
    ],
    "flag_default": [
      {"center": [0.07, 8.87, -4.99]}
    ],
    "map_bounds": [
      {"center": [-0.21, 7.75, -0.38], "size": [23.81, 13.86, 16.38]}
    ],
    "powerup_spawn": [
      {"center": [1.66, 8.05, -1.22]},
      {"center": [-1.49, 7.91, -1.23]},
      {"center": [2.63, 6.36, 1.4]},
      {"center": [-2.7, 6.36, 1.43]}
    ],
    "shadow_lower_bottom": [
      {"center": [0.07, 4.0, 6.32]}
    ],
    "shadow_lower_top": [
      {"center": [0.07, 4.75, 6.32]}
    ],
    "shadow_upper_bottom": [
      {"center": [0.07, 9.15, 6.32]}
    ],
    "shadow_upper_top": [
      {"center": [0.07, 13.82, 6.32]}
    ],
    "spawn": [
      {"center": [-7.26, 5.46, -3.1], "size": [1.16, 1.16, 1.16]},
      {"center": [7.38, 5.21, -2.79], "size": [1.16, 1.16, 1.16]}
    ]
  }
}